.bzrignore
COPYING
ChangeLog
INSTALL.txt
Makefile
README.txt
TODO.txt
setup.cfg
setup.py
docs/Makefile
docs/index.txt
docs/install.txt
docs/overview.txt
softwarefabrica/__init__.py
softwarefabrica.django.appserver.egg-info/PKG-INFO
softwarefabrica.django.appserver.egg-info/SOURCES.txt
softwarefabrica.django.appserver.egg-info/dependency_links.txt
softwarefabrica.django.appserver.egg-info/entry_points.txt
softwarefabrica.django.appserver.egg-info/namespace_packages.txt
softwarefabrica.django.appserver.egg-info/requires.txt
softwarefabrica.django.appserver.egg-info/top_level.txt
softwarefabrica.django.appserver.egg-info/zip-safe
softwarefabrica/django/__init__.py
softwarefabrica/django/appserver/__init__.py
softwarefabrica/django/appserver/bzrcachedrev.py
softwarefabrica/django/appserver/djangoserve.conf
softwarefabrica/django/appserver/djangoserve.py
softwarefabrica/django/appserver/finddata.py
softwarefabrica/django/appserver/translogger.py
softwarefabrica/django/appserver/version.py
softwarefabrica/django/appserver/wsgiserver.py
