Metadata-Version: 1.0
Name: softwarefabrica.django.appserver
Version: 1.0dev-BZR-r10-panta-elasticworld.org-20091023132843-vitk6k7e5qlvhej5
Summary: Django HTTP(S) application server
Home-page: http://cheeseshop.python.org/pypi/softwarefabrica.django.appserver/
Author: Marco Pantaleoni
Author-email: m.pantaleoni@softwarefabrica.org
License: GNU GPL v2
Download-URL: http://pypi.python.org/packages/source/s/softwarefabrica.django.appserver/softwarefabrica.django.appserver-1.0dev-BZR-r10-panta-elasticworld.org-20091023132843-vitk6k7e5qlvhej5.tar.gz
Keywords: django application server http https web
Platform: UNKNOWN
Classifier: Development Status :: 4 - Beta
Classifier: Framework :: Django
Classifier: Intended Audience :: Developers
Classifier: License :: OSI Approved :: GNU General Public License (GPL)
Classifier: Operating System :: OS Independent
Classifier: Programming Language :: Python :: 2.3
Classifier: Topic :: Software Development :: Libraries :: Python Modules
